paritydeals_sdk/__init__.py
paritydeals_sdk/checkout.py
paritydeals_sdk/client.py
paritydeals_sdk/constants.py
paritydeals_sdk/customers.py
paritydeals_sdk/entitlements.py
paritydeals_sdk/exceptions.py
paritydeals_sdk/py.typed
paritydeals_sdk/reporting.py
paritydeals_sdk/subscription.py
paritydeals_sdk/models/__init__.py
paritydeals_sdk/models/checkout.py
paritydeals_sdk/models/customers.py
paritydeals_sdk/models/entitlements.py
paritydeals_sdk/models/reporting.py
paritydeals_sdk/models/subscription.py
paritydeals_sdk-1.0.1.dist-info/licenses/LICENSE
paritydeals_sdk-1.0.1.dist-info/METADATA
paritydeals_sdk-1.0.1.dist-info/WHEEL
paritydeals_sdk-1.0.1.dist-info/top_level.txt
paritydeals_sdk-1.0.1.dist-info/RECORD
