Metadata-Version: 2.4
Name: paritydeals-sdk
Version: 1.0.1
Summary: A Python SDK for interacting with the ParityDeals API to report usage and events. Supports synchronous and asynchronous operations using a unified client.
Author-email: Geo Jacob / ParityDeals <geo@paritydeals.com>
License: MIT License
Project-URL: Homepage, https://github.com/paritydeals/paritydeals-python-sdk
Project-URL: Bug Tracker, https://github.com/paritydeals/paritydeals-python-sdk/issues
Keywords: sdk,api,paritydeals,reporting,events,usage,async,sync,httpx
Classifier: Intended Audience :: Developers
Classifier: License :: OSI Approved :: MIT License
Classifier: Operating System :: OS Independent
Classifier: Programming Language :: Python :: 3
Classifier: Programming Language :: Python :: 3.8
Classifier: Programming Language :: Python :: 3.9
Classifier: Programming Language :: Python :: 3.10
Classifier: Programming Language :: Python :: 3.11
Classifier: Programming Language :: Python :: 3.12
Classifier: Topic :: Software Development :: Libraries :: Python Modules
Classifier: Typing :: Typed
Requires-Python: >=3.8
License-File: LICENSE
Requires-Dist: httpx<1.0,>=0.23.0
Requires-Dist: pydantic<3.0,>=2.0
Provides-Extra: test
Requires-Dist: pytest>=7.0; extra == "test"
Requires-Dist: pytest-asyncio>=0.18; extra == "test"
Provides-Extra: dev
Dynamic: license-file
